buggerking/ThirdPartyNotices.txt
buggerking/__init__.py
buggerking/__main__.py
buggerking/_version.py
buggerking/public_api.py
buggerking/_vendored/__init__.py
buggerking/_vendored/_pydevd_packaging.py
buggerking/_vendored/_util.py
buggerking/_vendored/force_pydevd.py
buggerking/_vendored/pydevd/pydev_app_engine_debug_startup.py
buggerking/_vendored/pydevd/pydev_coverage.py
buggerking/_vendored/pydevd/pydev_pysrc.py
buggerking/_vendored/pydevd/pydev_run_in_console.py
buggerking/_vendored/pydevd/pydevconsole.py
buggerking/_vendored/pydevd/pydevd.py
buggerking/_vendored/pydevd/pydevd_file_utils.py
buggerking/_vendored/pydevd/pydevd_tracing.py
buggerking/_vendored/pydevd/setup_pydevd_cython.py
buggerking/_vendored/pydevd/_pydev_bundle/__init__.py
buggerking/_vendored/pydevd/_pydev_bundle/_pydev_calltip_util.py
buggerking/_vendored/pydevd/_pydev_bundle/_pydev_completer.py
buggerking/_vendored/pydevd/_pydev_bundle/_pydev_execfile.py
buggerking/_vendored/pydevd/_pydev_bundle/_pydev_filesystem_encoding.py
buggerking/_vendored/pydevd/_pydev_bundle/_pydev_getopt.py
buggerking/_vendored/pydevd/_pydev_bundle/_pydev_imports_tipper.py
buggerking/_vendored/pydevd/_pydev_bundle/_pydev_jy_imports_tipper.py
buggerking/_vendored/pydevd/_pydev_bundle/_pydev_log.py
buggerking/_vendored/pydevd/_pydev_bundle/_pydev_saved_modules.py
buggerking/_vendored/pydevd/_pydev_bundle/_pydev_sys_patch.py
buggerking/_vendored/pydevd/_pydev_bundle/_pydev_tipper_common.py
buggerking/_vendored/pydevd/_pydev_bundle/pydev_console_utils.py
buggerking/_vendored/pydevd/_pydev_bundle/pydev_import_hook.py
buggerking/_vendored/pydevd/_pydev_bundle/pydev_imports.py
buggerking/_vendored/pydevd/_pydev_bundle/pydev_ipython_console.py
buggerking/_vendored/pydevd/_pydev_bundle/pydev_ipython_console_011.py
buggerking/_vendored/pydevd/_pydev_bundle/pydev_is_thread_alive.py
buggerking/_vendored/pydevd/_pydev_bundle/pydev_localhost.py
buggerking/_vendored/pydevd/_pydev_bundle/pydev_log.py
buggerking-1.8.17.dist-info/licenses/LICENSE
buggerking-1.8.17.dist-info/METADATA
buggerking-1.8.17.dist-info/WHEEL
buggerking-1.8.17.dist-info/entry_points.txt
buggerking-1.8.17.dist-info/top_level.txt
buggerking-1.8.17.dist-info/RECORD
